snowpat/SnowLense/SnowLense.py
snowpat/SnowLense/Utils.py
snowpat/SnowLense/__init__.py
snowpat/SnowLense/plot_helpers_snowpack.py
snowpat/SnowLense/plot_snowpack.py
snowpat/SnowLense/plotting.py
snowpat/Utils/ACDD.py
snowpat/__init__.py
snowpat/icsv/__init__.py
snowpat/icsv/application_profile.py
snowpat/icsv/factory.py
snowpat/icsv/header.py
snowpat/icsv/icsv_file.py
snowpat/icsv/utility.py
snowpat/msgs.py
snowpat/pysmet/MetaData.py
snowpat/pysmet/SMET.py
snowpat/pysmet/__init__.py
snowpat/pysmet/pymset.py
snowpat/resources/snowpat.png
snowpat/snowpackreader/Snowpack.py
snowpat/snowpackreader/__init__.py
snowpat/snowpackreader/json_converter.py
snowpat/snowpackreader/snowpackreader.py
snowpat-0.8.7.dist-info/COPYING
snowpat-0.8.7.dist-info/METADATA
snowpat-0.8.7.dist-info/WHEEL
snowpat-0.8.7.dist-info/RECORD
