Metadata-Version: 2.1
Name: snowpat
Version: 0.8.7
Summary: 
Author: Patrick Leibersperger
Author-email: patrick.leibersperger@slf.ch
Requires-Python: >=3.9,<4.0
Classifier: Programming Language :: Python :: 3
Classifier: Programming Language :: Python :: 3.9
Classifier: Programming Language :: Python :: 3.10
Classifier: Programming Language :: Python :: 3.11
Classifier: Programming Language :: Python :: 3.12
Requires-Dist: datetime (>=5.5,<6.0)
Requires-Dist: h5py (>=3.5,<4.0)
Requires-Dist: matplotlib (>=3.8.3,<4.0.0)
Requires-Dist: numpy (>=1.26,<2.0)
Requires-Dist: pandas (>=2,<3)
Requires-Dist: xarray (>=2024.3.0,<2025.0.0)
